kwwutils/__init__.py
kwwutils/kwwutils.py
tests/_1_test.py
tests/__init__.py
kwwutils-0.1.17.dist-info/METADATA
kwwutils-0.1.17.dist-info/WHEEL
kwwutils-0.1.17.dist-info/top_level.txt
kwwutils-0.1.17.dist-info/RECORD
